[{"Name":"T1","Command":"T1","Id":0,"CameraId":0,"ShowId":0,"ExposureTIme":0.0,"Brightness":0,"Contrast":0,"Trigger":false,"RedoCount":0},{"Name":"T2","Command":"T2","Id":0,"CameraId":0,"ShowId":0,"ExposureTIme":0.0,"Brightness":0,"Contrast":0,"Trigger":false,"RedoCount":0},{"Name":"T3","Command":"T3","Id":0,"CameraId":0,"ShowId":0,"ExposureTIme":0.0,"Brightness":0,"Contrast":0,"Trigger":false,"RedoCount":0},{"Name":"T4","Command":"T4","Id":0,"CameraId":0,"ShowId":0,"ExposureTIme":0.0,"Brightness":0,"Contrast":0,"Trigger":false,"RedoCount":0},{"Name":"T5","Command":"T5","Id":0,"CameraId":0,"ShowId":0,"ExposureTIme":0.0,"Brightness":0,"Contrast":0,"Trigger":false,"RedoCount":0}]